LICENSE
README.md
setup.py
easytorch/__init__.py
easytorch/easytorch.py
easytorch/runner.py
easytorch.egg-info/PKG-INFO
easytorch.egg-info/SOURCES.txt
easytorch.egg-info/dependency_links.txt
easytorch.egg-info/requires.txt
easytorch.egg-info/top_level.txt
easytorch/config/__init__.py
easytorch/config/state.py
easytorch/data/__init__.py
easytorch/data/data.py
easytorch/data/datautils.py
easytorch/data/multiproc.py
easytorch/metrics/__init__.py
easytorch/metrics/loss.py
easytorch/metrics/metrics.py
easytorch/utils/__init__.py
easytorch/utils/ddp_check.py
easytorch/utils/logger.py
easytorch/utils/tensorutils.py
easytorch/vision/__init__.py
easytorch/vision/imageutils.py
easytorch/vision/plotter.py
easytorch/vision/transforms.py