Metadata-Version: 2.1
Name: easytorch
Version: 3.6.4
Summary: Easy Neural Network Experiments with pytorch
Home-page: https://github.com/sraashis/easytorch
Author: Aashis Khana1
Author-email: sraashis@gmail.com
License: MIT
Classifier: License :: OSI Approved :: MIT License
Classifier: Programming Language :: Python :: 3.7
License-File: LICENSE
